pisa/__init__.py
pisa/__main__.py
pisa/config.py
pisa/dispatcher/cluster_conf.py
pisa/dispatcher/dispatcher.py
pisa/dispatcher/task_list.py
pisa/ssh/ssh.py
pisa_ssh-0.1.9.dist-info/licenses/LICENSE
pisa_ssh-0.1.9.dist-info/METADATA
pisa_ssh-0.1.9.dist-info/WHEEL
pisa_ssh-0.1.9.dist-info/entry_points.txt
pisa_ssh-0.1.9.dist-info/top_level.txt
pisa_ssh-0.1.9.dist-info/RECORD
