Metadata-Version: 2.4
Name: pisa-ssh
Version: 0.1.9
Summary: Pseudo Infrastructure for Scalable Applications (PISA)
Author-email: Michael Hohenstein <michael@hohenste.in>
License: MIT
Project-URL: Homepage, https://mitchilaser.github.io/pisa/
Project-URL: Repository, https://github.com/MitchiLaser/pisa
Keywords: data,analysis,education,university,students,physics
Classifier: Development Status :: 5 - Production/Stable
Classifier: Intended Audience :: Education
Classifier: Intended Audience :: Science/Research
Classifier: Topic :: Education
Classifier: Topic :: Scientific/Engineering
Classifier: Topic :: Scientific/Engineering :: Physics
Classifier: Topic :: Scientific/Engineering :: Information Analysis
Classifier: Programming Language :: Python :: 3
Classifier: Programming Language :: Python :: 3.11
Classifier: Programming Language :: Python :: 3.12
Requires-Python: >=3.11
License-File: LICENSE
Provides-Extra: dev
Requires-Dist: build; extra == "dev"
Requires-Dist: twine; extra == "dev"
Dynamic: license-file
